{"cameraMode":{"drawMode":0,"name":"Shaded","section":"Shading Mode"},"sceneLighting":true,"audioPlay":false,"sceneViewState":{"m_AlwaysRefresh":false,"showFog":true,"showSkybox":true,"showFlares":true,"showImageEffects":true,"showParticleSystems":true,"showVisualEffectGraphs":true,"m_FxEnabled":true},"in2DMode":false,"pivot":{"x":926.4873046875,"y":548.4306640625,"z":-9.169189453125},"rotation":{"x":0.016499577090144159,"y":-0.0014981301501393319,"z":0.000023951562980073504,"w":0.9998493790626526},"size":627.1245727539063,"orthographic":false}