{"cameraMode":{"drawMode":0,"name":"Shaded","section":"Shading Mode"},"sceneLighting":true,"audioPlay":false,"sceneViewState":{"m_AlwaysRefresh":false,"showFog":true,"showSkybox":true,"showFlares":true,"showImageEffects":true,"showParticleSystems":true,"showVisualEffectGraphs":true,"m_FxEnabled":true},"in2DMode":false,"pivot":{"x":-60.79856491088867,"y":1.704681158065796,"z":0.30745404958724978},"rotation":{"x":0.10374472290277481,"y":-0.26978781819343569,"z":0.029255466535687448,"w":0.9568532705307007},"size":1.6114579439163209,"orthographic":false}